azure_teams_bot/__init__.py
azure_teams_bot/adapters.py
azure_teams_bot/conf.py
azure_teams_bot/config.py
azure_teams_bot/service.py
azure_teams_bot/version.py
azure_teams_bot/bots/BadgeBot.py
azure_teams_bot/bots/ChatBot.py
azure_teams_bot/bots/ProfileBot.py
azure_teams_bot/bots/__init__.py
azure_teams_bot/bots/abstract.py
azure_teams_bot/bots/base.py
azure_teams_bot/bots/card.py
azure_teams_bot/bots/echo.py
azure_teams_bot/bots/models.py
azure_teams_bot/bots/dialogs/__init__.py
azure_teams_bot/bots/dialogs/badge.py
azure_teams_bot/bots/dialogs/profile.py
azure_teams_bot/bots/helpers/__init__.py
azure_teams_bot/bots/interfaces/__init__.py
azure_teams_bot/bots/interfaces/messages.py
azure_teams_bot-0.0.1.dist-info/METADATA
azure_teams_bot-0.0.1.dist-info/WHEEL
azure_teams_bot-0.0.1.dist-info/top_level.txt
azure_teams_bot-0.0.1.dist-info/RECORD
